sphinx_rtd_eth_theme/__init__.py
sphinx_rtd_eth_theme/breadcrumbs.html
sphinx_rtd_eth_theme/footer.html
sphinx_rtd_eth_theme/layout.html
sphinx_rtd_eth_theme/search.html
sphinx_rtd_eth_theme/searchbox.html
sphinx_rtd_eth_theme/theme.conf
sphinx_rtd_eth_theme/versions.html
sphinx_rtd_eth_theme/locale/sphinx.pot
sphinx_rtd_eth_theme/locale/de/LC_MESSAGES/sphinx.mo
sphinx_rtd_eth_theme/locale/de/LC_MESSAGES/sphinx.po
sphinx_rtd_eth_theme/locale/en/LC_MESSAGES/sphinx.mo
sphinx_rtd_eth_theme/locale/en/LC_MESSAGES/sphinx.po
sphinx_rtd_eth_theme/locale/es/LC_MESSAGES/sphinx.mo
sphinx_rtd_eth_theme/locale/es/LC_MESSAGES/sphinx.po
sphinx_rtd_eth_theme/locale/et/LC_MESSAGES/sphinx.mo
sphinx_rtd_eth_theme/locale/et/LC_MESSAGES/sphinx.po
sphinx_rtd_eth_theme/locale/fr/LC_MESSAGES/sphinx.mo
sphinx_rtd_eth_theme/locale/fr/LC_MESSAGES/sphinx.po
sphinx_rtd_eth_theme/locale/nl/LC_MESSAGES/sphinx.mo
sphinx_rtd_eth_theme/locale/nl/LC_MESSAGES/sphinx.po
sphinx_rtd_eth_theme/locale/pt_BR/LC_MESSAGES/sphinx.mo
sphinx_rtd_eth_theme/locale/pt_BR/LC_MESSAGES/sphinx.po
sphinx_rtd_eth_theme/locale/ru/LC_MESSAGES/sphinx.mo
sphinx_rtd_eth_theme/locale/ru/LC_MESSAGES/sphinx.po
sphinx_rtd_eth_theme/locale/sv/LC_MESSAGES/sphinx.mo
sphinx_rtd_eth_theme/locale/sv/LC_MESSAGES/sphinx.po
sphinx_rtd_eth_theme/locale/tr/LC_MESSAGES/sphinx.mo
sphinx_rtd_eth_theme/locale/tr/LC_MESSAGES/sphinx.po
sphinx_rtd_eth_theme/locale/zh_CN/LC_MESSAGES/sphinx.mo
sphinx_rtd_eth_theme/locale/zh_CN/LC_MESSAGES/sphinx.po
sphinx_rtd_eth_theme/static/css/badge_only.css
sphinx_rtd_eth_theme/static/css/theme.css
sphinx_rtd_eth_theme/static/css/fonts/DINNextW1G-Medium.otf
sphinx_rtd_eth_theme/static/css/fonts/DINNextW1G-Regular.otf
sphinx_rtd_eth_theme/static/css/fonts/fontawesome-webfont.eot
sphinx_rtd_eth_theme/static/css/fonts/fontawesome-webfont.svg
sphinx_rtd_eth_theme/static/css/fonts/fontawesome-webfont.ttf
sphinx_rtd_eth_theme/static/css/fonts/fontawesome-webfont.woff
sphinx_rtd_eth_theme-0.5.0.dist-info/LICENSE
sphinx_rtd_eth_theme-0.5.0.dist-info/METADATA
sphinx_rtd_eth_theme-0.5.0.dist-info/WHEEL
sphinx_rtd_eth_theme-0.5.0.dist-info/entry_points.txt
sphinx_rtd_eth_theme-0.5.0.dist-info/top_level.txt
sphinx_rtd_eth_theme-0.5.0.dist-info/RECORD
